Workbook

Sheet 읽는 법
A1: KBTI 인간 코딩 — 시험 세트 180건 · 코더 B
A3: 무엇인가 | B3: LLM 코딩과 GDELT 코딩을 사람 기준으로 재기 위한 독립 코딩입니다. 두 분이 같은 기사를 따로 코딩하고, 먼저 사람끼리의 일치도를 냅니다. 그 값이 LLM 이 넘어야 할 천장입니다.
A4: 유일한 지침 | B4: 코드북 v1.1. 이 시트는 코드북을 대체하지 않습니다. 판단이 서지 않으면 코드북을 보시고, 그래도 없으면 메모에 남기세요.
A6: 어떻게 | B6: '코딩' 시트의 노란 칸만 채웁니다. 드롭다운이 있습니다.
B7: 제목과 두 단락만 읽고 판정합니다. 기사 원문을 찾아보지 않습니다.
B8: V1 이 '아니오'나 '판정불가'면 V2~V5 는 비워 둡니다.
B9: '코드 확인' 열은 자동입니다 — V5 에 고른 코드의 이름이 뜹니다. 손대지 마세요.
B10: '확신' 은 판정불가로 돌릴까 망설인 건에 '낮음' 을 답니다.
A12: 반드시 | B12: 판정불가를 아끼지 마세요. 억지로 고른 값이 일치도를 올리고 지수를 망칩니다.
B13: 애매한 건은 메모에 한 줄 남겨 주세요. 코드북을 고치는 근거가 됩니다.
B14: 다른 코더와 상의하지 않습니다. 상의하면 일치도가 측정값이 아니게 됩니다.
B15: GDELT 배정과 LLM 코딩은 일부러 넣지 않았습니다.
A17: 표본 | B17: 복원한 감사 로그 37일치에서 제목이 있는 고유 기사 1,748건 중 날짜 비례로 180건. 난수씨 20261021 고정.
B18: 코드북을 만들고 고칠 때 쓴 9월 20일·10월 3일 기사는 전부 뺐습니다.
B19: 제목만 있고 단락이 빈 기사가 31건 들어 있습니다. 모집단의 실제 모습이며, 코드북 9장대로 제목이 사건을 다 말하면 코딩합니다.
A21: 분량 | B21: 180건에 3시간 30분 안팎. 한 번에 끝낼 필요 없습니다.
A22: 진행 | B22: =COUNTA(코딩!F4:F183)&" / 180 건 완료" -> 0 / 180 건 완료

Sheet 코딩
A1: 노란 칸만 채웁니다. 3행은 형식을 보여 주는 예시이니 지우고 시작하세요.
A2: ID | B2: 날짜 | C2: 제목 | D2: 첫 단락 | E2: 둘째 단락 | F2: V1 관련 | G2: V2 상대국 | H2: V3 방향 | I2: V4 주제 | J2: V5 코드 | K2: 코드 확인 | L2: 확신 | M2: 메모
A3: 예시 | B3: 2026-09-24 | C3: North Korea fires two ballistic missiles off east coast | D3: North Korea has launched two short-range ballistic missiles towards the sea, South Korea's military says. | F3: 예 | G3: PRK | H3: threat | I3: 군사 | J3: 150 | K3: =IFERROR(INDEX(코드집!$B:$B,MATCH($J3,코드집!$A:$A,0)),"") -> EXHIBIT FORCE POSTURE | L3: 높음 | M3: R1 — 바다로 쏜 시험이므로 150, 190 아님
A4: 1 | B4: 2026-10-01 | C4: South Korea leader urges Pyongyang dialogue - World News | D4: South Korean President Lee Jae Myung delivers a speech during the 78th Armed Forces Day at a military base in Gyeryong on October 1, 2026. (AFP Photo) | E4: South Korean President Lee Jae Myung urged North Korea on Oct. 1 to return to dialogue, a day after Seoul ’s military demanded an apology over a blast in the Demilitarized Zone ( DMZ ) that severely injured three South Korean soldiers. | K4: =IFERROR(INDEX(코드집!$B:$B,MATCH($J4,코드집!$A:$A,0)),"")
A5: 2 | B5: 2026-09-21 | C5: N Korea fires 2 ballistic missiles off east coast - Oman Observer | D5: SEOUL: North Korea fired two short-range ballistic missiles into the sea off its eastern coast on Sunday, South Korea's military said, with the second flying more than 600 kilometres. The launches came days after Pyongyang reasserted its status as a nuclear-armed state and rejected a United Nations resolution demanding it halt its nuclear activities. South Korea's military said the first missile was launched at around 3:00 pm from the Wonsan area and flew around 450 kilometres into the East Sea, a body of water also called the Sea of Japan. "Our military detected an additional short-range ballistic missile launched from the Wonsan area of North Korea towards the East Sea at around 5:50 pm," South Korea's Joint Chiefs of Staff (JCS) said. The second missile "flew more than 600 kilometres, and South Korean and US authorities are conducting a detailed analysis to determine its exact specifications," it said. The JCS said South Korea, the United States and Japan had been "tracking and sharing relevant developments from the initial stage of the launch". Japan lodged a "stern protest" with North Korea over the launches, condemning them as a threat to regional peace and security, the Kyodo news agency cited the government as saying. South Korea's presidential National Security Office convened an emergency security meeting following the first launch and assessed its impact on national security, the presidential office said. The government called on Pyongyang to "immediately cease" its ballistic missile launches, describing Sunday's firings as a "grave act" that violated UN Security Council resolutions. The launches came eight days after North Korea fired multiple short-range ballistic missiles towards the East Sea as part of what it later described as a joint firepower drill. That exercise involved long-range artillery and missiles, with the weapons "hitting the targets with 100 per cent accuracy", state media reported. North Korea accused "hostile forces" of seeking to end the country's nuclear programme during this week's General Conference of the International Atomic Energy Agency (IAEA). A foreign ministry spokesperson said the IAEA resolution "has no effect on the DPRK's position as a nuclear weapons state", using the acronym for North Korea's official name. The North's status as a nuclear power is "guaranteed by the actual nuclear deterrent and irreversibly and permanently fixed by the supreme law of the state", the spokesperson said. Kim Yo Jong, the powerful sister of North Korean leader Kim Jong Un, recently said the country's nuclear-armed status was "absolute" and called those hoping for its denuclearisation "idiots". US President Donald Trump said in August that North Korea possessed 57 "very powerful" nuclear weapons, while South Korea has put the figure at between 80 and 120. — AFP | E5: SEOUL: North Korea fired two short-range ballistic missiles into the sea off its eastern coast on Sunday, South Korea's military said, with the second flying more than 600 kilometres. The launches came days after Pyongyang reasserted its status as a nuclear-armed state and rejected a United Nations resolution demanding it halt its nuclear activities. South Korea's military said the first missile was launched at around 3:00 pm from the Wonsan area and flew around 450 kilometres into the East Sea, a body of water also called the Sea of Japan. "Our military detected an additional short-range ballistic missile launched from the Wonsan area of North Korea towards the East Sea at around 5:50 pm," South Korea's Joint Chiefs of Staff (JCS) said. The second missile "flew more than 600 kilometres, and South Korean and US authorities are conducting a detailed analysis to determine its exact specifications," it said. The JCS said South Korea, the United States and Japan had been "tracking and sharing relevant developments from the initial stage of the launch". Japan lodged a "stern protest" with North Korea over the launches, condemning them as a threat to regional peace and security, the Kyodo news agency cited the government as saying. South Korea's presidential National Security Office convened an emergency security meeting following the first launch and assessed its impact on national security, the presidential office said. The government called on Pyongyang to "immediately cease" its ballistic missile launches, describing Sunday's firings as a "grave act" that violated UN Security Council resolutions. The launches came eight days after North Korea fired multiple short-range ballistic missiles towards the East Sea as part of what it later described as a joint firepower drill. That exercise involved long-range artillery and missiles, with the weapons "hitting the targets with 100 per cent accuracy", state media reported. North Korea accused "hostile forces" of seeking to end the country's nuclear programme during this week's General Conference of the International Atomic Energy Agency (IAEA). A foreign ministry spokesperson said the IAEA resolution "has no effect on the DPRK's position as a nuclear weapons state", using the acronym for North Korea's official name. The North's status as a nuclear power is "guaranteed by the actual nuclear deterrent and irreversibly and permanently fixed by the supreme law of the state", the spokesperson said. Kim Yo Jong, the powerful sister of North Korean leader Kim Jong Un, recently said the country's nuclear-armed status was "absolute" and called those hoping for its denuclearisation "idiots". US President Donald Trump said in August that North Korea possessed 57 "very powerful" nuclear weapons, while South Korea has put the figure at between 80 and 120. — AFP | K5: =IFERROR(INDEX(코드집!$B:$B,MATCH($J5,코드집!$A:$A,0)),"")
A6: 3 | B6: 2026-10-09 | C6: Пхеньян против планов Сеула оказать помощь КНДР l KBS WORLD Russian | D6: Политика Президент РК поздравил граждан с Днём корейской письменности 2026-10-09 12:22:28 | K6: =IFERROR(INDEX(코드집!$B:$B,MATCH($J6,코드집!$A:$A,0)),"")
A7: 4 | B7: 2026-10-20 | C7: Jutarnji list - Šire se neprovjerene vijesti o stanju Kim Jong-una, izvanredno se obratila njegova sestra | K7: =IFERROR(INDEX(코드집!$B:$B,MATCH($J7,코드집!$A:$A,0)),"")
A8: 5 | B8: 2026-09-22 | C8: [사설]윤곽 드러난 대미투자, 끝까지 수익성 확보해야 - 파이낸셜뉴스 | D8: 정부의 대미 전략투자 윤곽이 드러났다. 정부는 22일 국회에 투자 1호 사업으로 미국 텍사스 엔시날 가스복합발전소 건설을 추진하겠다고 보고했다. 미국 내 대형 원전 8기 건설과 알래스카 액화천연가스(LNG) 개발은 2·3호 협의 과제로 제시했다. 후속협상에서도 끝까지 국익을 최우선 기준으로 삼아야 할 것이다. | E8: 1호인 엔시날 가스발전에 대해 정부는 사업성을 검토한 결과 수익성이 충분히 있는 것으로 판단했다고 한다. 인공지능(AI) 데이터센터와 첨단 반도체 공장 등이 잇따라 들어서는 텍사스에서 전력 수요가 빠르게 증가하는 점도 긍정적이다. 총사업비 223억달러를 투입해 20년간 432억9000만~454억300만달러의 수입을 거둘 수 있어 원리금 회수가 가능하다는 게 정부의 분석이다. 처음부터 6.3GW를 한꺼번에 짓지 않고 1.4GW부터 시작해 실제 수요와 경제성을 확인하며 단계적으로 증설하는 방식도 위험을 낮추는 안전장치가 될 수 있다. | K8: =IFERROR(INDEX(코드집!$B:$B,MATCH($J8,코드집!$A:$A,0)),"")
A9: 6 | B9: 2026-09-25 | C9: Tajni transfer više nije tajan: Seul zamjerio Zelenskom kršenje dogovora | advance.hr | D9: Piše advance.hr | E9: Južnokorejski predsjednik Lee Jae-myung izrazio je nezadovoljstvo Volodimirom Zelenskim nakon što je ukrajinski predsjednik pred Općom skupštinom UN-a objavio da su dvojica sjevernokorejskih ratnih zarobljenika prebačena u Južnu Koreju. Lee tvrdi da su se Seul i Kijev dogovorili kako će transfer ostati tajan te je ukrajinsko kršenje dogovora nazvao "vrlo razočaravajućim" . | K9: =IFERROR(INDEX(코드집!$B:$B,MATCH($J9,코드집!$A:$A,0)),"")
A10: 7 | B10: 2026-09-17 | C10: North Korea launches missile salvo after US-South Korea-Japan drills | South China Morning Post | D10: The ballistic missiles, which flew about 250km, were fired despite Donald Trump’s recent push for talks with Kim Jong-un | E10: The missiles were launched at around 5.20am and flew about 250 km (155 miles), the JCS said in a statement, ‌adding that South Korean and US authorities were conducting a detailed analysis of their specifications. | K10: =IFERROR(INDEX(코드집!$B:$B,MATCH($J10,코드집!$A:$A,0)),"")
A11: 8 | B11: 2026-09-25 | C11: Trump s pompou přijal prezidenta Číny: Honosná státní večeře! Na řadě je Putin? | Blesk.cz | D11: Nejmocnější muž světa si zve další lídry supervelmocí. Ve čtvrtek hostil s velkou slávou čínského prezidenta, pozvání na prosinec teď dostal i ten ruský. Ten však zatím dává přednost jiné společnosti… | E11: Červený koberec, armádní uvítání s vojenskou kapelou, dělostřeleckou salvou a přeletem burácivých bombardérů B-1 – dohromady 479 mužů a žen v uniformách – či galavečeře s nejbohatšími muži světa jako Elon Musk a Jeff Bezos . Takové přivítání přichystal Donald Trump s Melanií po boku pro Si Ťin-pchinga a jeho první dámu Pcheng Li-jüan , jak vypočetl web rádia NPR . A to na oplátku za svou návštěvu Pekingu v polovině května. | K11: =IFERROR(INDEX(코드집!$B:$B,MATCH($J11,코드집!$A:$A,0)),"")
A12: 9 | B12: 2026-09-21 | C12: N. Korea launches 2 missiles toward sea | Northwest Arkansas Democrat-Gazette | D12: SEOUL, South Korea -- North Korea launched two short-range ballistic missiles toward the sea on Sunday, South Korea's military said, days after the North threatened to bolster its nuclear deterrent capabilities and respond to what it called U.S. hostilities. | E12: The launches were the latest in a series of weapons demonstrations by North Korea even after U.S. President Donald Trump scaled back a joint military exercise with South Korea last month in an apparent effort to revive diplomacy with the North's leader, Kim Jong Un. | K12: =IFERROR(INDEX(코드집!$B:$B,MATCH($J12,코드집!$A:$A,0)),"")
A13: 10 | B13: 2026-10-06 | C13: Южна Корея е доставила над 176 хил. тона гориво на Русия с танкери, част от които са под санкции ᐉ Новини от Fakti.bg - Свят | ФАКТИ.БГ | D13: 6 Октомври, 2026 16:34, обновена 6 Октомври, 2026 16:32 1 605 22 | E13: Южна Корея е доставила гориво на Русия с танкери, три от които са под санкции на Великобритания и Европейския съюз. Това се случва на фона на опитите на Москва да компенсира недостига на горива, причинен от прекъсвания в работата на нефтопреработвателните заводи, съобщава „Гардиън“, позовавайки се на анализ на пристанищни регистри и данни за проследяване на кораби, предава Фокус. | K13: =IFERROR(INDEX(코드집!$B:$B,MATCH($J13,코드집!$A:$A,0)),"")
A14: 11 | B14: 2026-09-19 | C14: South Korea, US discuss Seoul’s role in Middle East and investment pact | The Straits Times | D14: Sign up now: Get ST's newsletters delivered to your inbox | E14: US Secretary of State Marco Rubio (left) and South Korean Foreign Minister Cho Hyun during a trilateral meeting on the sidelines of the NATO leaders’ summit in Ankara on July 7. | K14: =IFERROR(INDEX(코드집!$B:$B,MATCH($J14,코드집!$A:$A,0)),"")
A15: 12 | B15: 2026-09-17 | C15: PM Han, AmCham seek deeper Korea-US investment ties - The Korea Herald | K15: =IFERROR(INDEX(코드집!$B:$B,MATCH($J15,코드집!$A:$A,0)),"")
A16: 13 | B16: 2026-10-12 | C16: North Korea fires multiple ballistic missiles, fourth test in a month | NK News | D16: Get behind the headlines | E16: North Korea fired multiple suspected ballistic missiles on Monday morning, according to Japanese and South Korean military authorities, the country’s fourth apparent missile test in the last month . | K16: =IFERROR(INDEX(코드집!$B:$B,MATCH($J16,코드집!$A:$A,0)),"")
A17: 14 | B17: 2026-10-16 | C17: "일본서 보던 옷이 여기 있네"…무신사 성수에 온 '조조타운' [현장] | D17: [아이뉴스24 구서윤 기자] 서울 성수동 무신사 스토어 성수에 들어서자 레이스와 리본으로 장식한 원피스부터 넉넉한 실루엣의 캐주얼웨어까지 일본 패션 브랜드의 옷들이 눈앞에 펼쳐졌다. | E17: 옷걸이마다 브랜드 특유의 색깔이 묻어났다. 국내 매장에서는 보기 드문 일본어 상품 설명과 엔화 가격표도 그대로 달려 있었다. 일본 여행 중 찾아가던 브랜드를 서울에서 직접 살펴보고 입어볼 수 있는 공간이었다. | K17: =IFERROR(INDEX(코드집!$B:$B,MATCH($J17,코드집!$A:$A,0)),"")
A18: 15 | B18: 2026-10-06 | C18: South Korea, US aligned on North Korea policy, denuclearisation of Korean Peninsula: FM Cho | D18: Seoul, Oct 6 : South Korean Foreign Minister Cho Hyun said Tuesday that South Korea and the United States are aligned in their North Korea policy and remain committed to the goal of denuclearising the Korean Peninsula. | E18: "Through multiple summit meetings, South Korea and the US have confirmed their aligned policy stance toward North Korea and their commitment to coordination," Cho said during a parliamentary audit of the foreign ministry. | K18: =IFERROR(INDEX(코드집!$B:$B,MATCH($J18,코드집!$A:$A,0)),"")
A19: 16 | B19: 2026-09-30 | C19: ‘Kim Jong Un a friend’: Trump's reasoning on why North Korea can have nuclear weapons but Iran cannot | World News | D19: US President Donald Trump has once again spotlighted his close relationship with North Korean leader Kim Jong Un. Trump made the remarks on Tuesday while answering a question about why North Korea could possess nuclear weapons while Iran was being prevented from acquiring them. | E19: “He happens to be a friend of mine. Kim Jong Un is a friend of mine,” the US President said. “He likes Trump…I’m about the only person in the entire world that he likes, and I like him. As long as I'm around, he's going to be fine. You know why? Because he respects me and he likes me.” | K19: =IFERROR(INDEX(코드집!$B:$B,MATCH($J19,코드집!$A:$A,0)),"")
A20: 17 | B20: 2026-10-09 | C20: FACT FOCUS: Trump says tariffs have brought more US auto factories. His numbers are off. | Business | dailygazette.com | D20: FILE - Cars are pictured on the assembly line at the BMW Spartanburg plant in Greer, S.C., October 19, 2022. | E20: DETROIT (AP) — As President Donald Trump travels the country to rally support for Republican candidates ahead of the midterm elections, he is touting his economic agenda and crediting GOP-backed tariffs with industry growth — including what he says are more vehicle manufacturing plants all over the country. | K20: =IFERROR(INDEX(코드집!$B:$B,MATCH($J20,코드집!$A:$A,0)),"")
A21: 18 | B21: 2026-09-17 | C21: De la autonomía en defensa a la cooperación industrial: la experiencia surcoreana y las nuevas posibilidades para América Latina | D21: El pasado mes de julio, el presidente Lee Jae Myung visitó sucesivamente Brasil , Chile y Argentina . En particular, la visita a Chile fue la primera visita oficial de un presidente surcoreano en 11 años, y ambos países acordaron ampliar la cooperación no solo en minerales críticos, energía, comercio e inversión, sino también en seguridad pública, defensa, infraestructura y asuntos marítimos. En este contexto, no basta con interpretar la cooperación en defensa entre Corea del Sur y América Latina únicamente como la aparición de un nuevo proveedor de sistemas de armas. Para comprender la industria de defensa surcoreana, conviene partir de una pregunta: ¿Por qué Corea del Sur comenzó a construir una industria de defensa propia? Esta pregunta guarda ciertos puntos de contacto con las preocupaciones actuales de Chile y de algunos países latinoamericanos que buscan reforzar simultáneamente sus capacidades de defensa, su base industrial y su autonomía tecnológica. Este artículo es la primera entrega de una serie destinada a presentar la industria de defensa surcoreana a los lectores de Infodefensa. En ella se examinará cómo Corea del Sur fue construyendo sus capacidades nacionales de defensa y qué orientaciones de cooperación internacional están emergiendo hoy tanto en los sistemas terrestres como en los nuevos ámbitos de seguridad. Una industria nacida de la necesidad Uno de los principales puntos de inflexión en el desarrollo de la industria de defensa surcoreana fue la doctrina Nixon de 1969. La reducción de las fuerzas estadounidenses en Corea asociada a aquella doctrina fue uno de los factores que impulsaron a Corea del Sur a reforzar de forma más sistemática su capacidad de defensa autónoma, un proceso que posteriormente se concretó en programas de modernización de las Fuerzas Armadas . La cuestión que afrontaba entonces Corea del Sur era clara. ¿Qué capacidades debía ser capaz de asegurar por sí misma, aun manteniendo su alianza? Por ello, la autonomía en defensa surcoreana se desarrolló como un proceso de ampliación de las responsabilidades y capacidades propias, manteniendo al mismo tiempo la alianza y la cooperación internacional. A partir de entonces, Corea del Sur continuó desarrollando su base industrial de defensa en paralelo con la modernización de sus fuerzas armadas. Esa acumulación de capacidades a lo largo de varias décadas condujo al desarrollo y a la proyección internacional de sistemas terrestres como el obús autopropulsado K9 , el carro de combate K2 y vehículos blindados como Tigon y Redback . K2 y K9: de la exportación a la cooperación industrial Uno de los casos más destacados de la expansión internacional de los sistemas terrestres surcoreanos es Polonia . En 2022, Corea del Sur y Polonia suscribieron acuerdos de cooperación en defensa que incluían, entre otros sistemas, carros de combate K2 y obuses autopropulsados K9. En acuerdos posteriores sobre el K2 se incorporaron planes para desarrollar la versión K2PL adaptada a las necesidades de las Fuerzas Armadas polacas y para ensamblar y producir localmente una parte significativa de los vehículos mediante la cooperación entre empresas de defensa surcoreanas y polacas. Esto muestra una ampliación del modelo de cooperación: desde la exportación tradicional de sistemas terminados hacia esquemas que incorporan una mayor participación de la industria local. La cooperación internacional vinculada al K9 también se ha ampliado. Hanwha Aerospace suministra este sistema a varios países de la OTAN , entre ellos Finlandia y Rumanía , y en febrero de 2026 inició en Rumanía la construcción de una instalación para la producción local del K9. Sin embargo, lo más relevante de estos casos es cómo combinar la adquisición de sistemas de armas con la participación de la industria local, la producción y el desarrollo de capacidades de apoyo logístico a largo plazo. Se trata también de una cuestión de política industrial para los países que buscan modernizar sus fuerzas armadas sin renunciar al mantenimiento o al desarrollo de su propia base industrial de defensa. Fidae 2026 y Tigon Este cambio también puede observarse en América Latina. Fidae 2026 , celebrada en Santiago de Chile en abril, reunió a 451 empresas de 35 países y se consolidó como una de las principales ferias latinoamericanas de los sectores aeroespacial, defensa y seguridad. En la feria, Hanwha presentó el obús autopropulsado K9, el sistema de lanzacohetes múltiple Chunmoo y el vehículo Tigon MCV . La información oficial de Fidae presentó al Tigon como un vehículo blindado multipropósito capaz de integrar diferentes sistemas de armas en función de los requisitos de misión. No obstante, más interesante que la propia plataforma Tigon fue la modalidad de cooperación entre una empresa surcoreana y una empresa española anunciada durante Fidae. Hanwha Aerospace e Indra Group firmaron en Fidae 2026 un memorando de entendimiento para proponer una solución conjunta al futuro programa de vehículos blindados del Ejército de Chile y ampliar posteriormente la cooperación hacia otros proyectos terrestres en América Latina. De acuerdo con la estructura de cooperación anunciada, Hanwha aporta la plataforma blindada Tigon, mientras que Indra aporta el Mission System Equipment que incluye capacidades de conectividad, conciencia situacional y C2 . Este caso demuestra que la cooperación en defensa entre Corea del Sur, España y América Latina no tiene por qué limitarse a un modelo en el que un país suministra un sistema terminado a otro. También es posible combinar una plataforma surcoreana con tecnologías españolas de sistemas de misión y adaptarlas a los requisitos operativos de Chile y de otros países latinoamericanos. La pregunta que plantea Chile La relevancia de este tipo de cooperación industrial también puede entenderse a partir de la propia política de defensa chilena. En documentos oficiales de 2026, el Ministerio de Defensa Nacional de Chile vinculó la defensa con la base productiva y tecnológica del país y planteó el fortalecimiento de la autonomía, la soberanía tecnológica y las capacidades polivalentes. Durante la inauguración de Fidae 2026, el Ministerio de Defensa chileno también destacó el fortalecimiento de la industria nacional de defensa y el desarrollo de capacidades espaciales propias, vinculando tecnología y soberanía. Esto no significa necesariamente que todos los sistemas de armas deban producirse de forma autónoma dentro del país. La cuestión se acerca más a cómo utilizar la cooperación internacional y, al mismo tiempo, asegurar las tecnologías esenciales y las capacidades propias de operación, mantenimiento y sostenimiento. La pregunta a la que Corea del Sur se enfrentó en el pasado presentaba ciertos elementos similares: no solo cómo adquirir los sistemas necesarios, sino también cómo operarlos, mantenerlos y convertirlos gradualmente en capacidades acumuladas dentro del propio país. Naturalmente, la experiencia surcoreana no puede trasladarse de manera mecánica a Chile ni a otros países latinoamericanos. Sin embargo, existe una cuestión compartida: encontrar un equilibrio adecuado entre la cooperación internacional y el fortalecimiento de las capacidades nacionales. Una nueva concepción de la autonomía en defensa Hoy el alcance de esta cuestión es mucho mayor. Si en la Corea del Sur de los años setenta uno de los principales objetivos de la autonomía en defensa era desarrollar fuerzas convencionales y establecer una base nacional para producir el equipo necesario, el entorno de seguridad actual exige algo más. Drones y sistemas no tripulados, ciberataques, guerra electrónica, amenazas contra las redes de comunicaciones y los datos, vulnerabilidades de los activos espaciales y crimen organizado transnacional están ampliando rápidamente el espectro de riesgos de seguridad. Estos cambios están ampliando también el propio concepto de capacidad de defensa. Ya no importa únicamente el rendimiento de plataformas tradicionales como carros de combate, vehículos blindados u obuses autopropulsados. Cada vez resulta más importante la capacidad de integrarlas eficazmente con C4I , inteligencia, vigilancia y reconocimiento, guerra electrónica, sistemas antidrones, ciberdefensa y redes de datos. Nuevas capacidades para América Latina Esta cuestión también es relevante para América Latina. No puede afirmarse que todos los países latinoamericanos sigan una misma política de seguridad. Sin embargo, las tendencias observadas en Fidae y en la reciente política de defensa chilena muestran una creciente atención no solo a las capacidades militares tradicionales, sino también al espacio, la ciberseguridad, los sistemas no tripulados, la defensa aérea y los radares. Por ello, la futura cooperación entre Corea del Sur y América Latina tampoco tiene por qué limitarse a plataformas terrestres tradicionales como el K9 o el Tigon. Existen posibilidades de ampliar la cooperación hacia ámbitos como C4I, inteligencia, vigilancia y reconocimiento, sistemas antidrones, guerra electrónica, ciberdefensa y procesamiento de información basado en inteligencia artificial. Más importante que el producto es la forma de cooperar Las condiciones históricas de Corea del Sur son diferentes de las de otros países y la trayectoria de su industria de defensa tampoco constituye un modelo universal que pueda reproducirse en cualquier lugar. No obstante, la experiencia de un país que partió de una fuerte dependencia del equipamiento y de la tecnología del exterior y que gradualmente amplió su propia base industrial de defensa y sus capacidades de desarrollo puede ofrecer un punto de referencia para países que buscan abordar simultáneamente la modernización militar y el fortalecimiento industrial. La estructura debe adaptarse a la base industrial, los requerimientos operativos, el nivel tecnológico y los objetivos de política pública de cada socio. De una preocupación común a la cooperación Lo que Corea del Sur puede compartir con los responsables de defensa y de industria de América Latina no se limita a determinados sistemas de armas. Tras la doctrina Nixon, Corea del Sur se enfrentó a una pregunta fundamental: ¿Cómo reforzar sus propias capacidades de defensa manteniendo al mismo tiempo la alianza y la cooperación internacional? Hoy el alcance de esa pregunta es todavía mayor. En un entorno en el que los Estados deben responder tanto a amenazas militares tradicionales como a riesgos cibernéticos, sistemas no tripulados, guerra electrónica y amenazas contra las cadenas de suministro y las infraestructuras críticas, el reto consiste en asegurar de manera sostenible las capacidades nacionales necesarias. En el proceso por el cual Chile y otros países latinoamericanos buscan respuestas adaptadas a sus propias circunstancias, Corea del Sur puede ser uno de sus socios de cooperación. La posibilidad de avanzar más allá de una relación Buyer-Seller hacia una Industrial and Security Partnership comienza precisamente aquí. Sobre el autor Hwang Jung-han es asesor de la Asociación Corea-América Latina y autor de «¿Por qué Chile ahora?», el primer libro coreano en presentar de manera integral la política, la economía, la sociedad y la cultura de Chile. Se desempeñó como ministro consejero y cónsul general en la Embajada de la República de Corea en Chile. | E21: El pasado mes de julio, el presidente Lee Jae Myung visitó sucesivamente Brasil , Chile y Argentina . En particular, la visita a Chile fue la primera visita oficial de un presidente surcoreano en 11 años, y ambos países acordaron ampliar la cooperación no solo en minerales críticos, energía, comercio e inversión, sino también en seguridad pública, defensa, infraestructura y asuntos marítimos. | K21: =IFERROR(INDEX(코드집!$B:$B,MATCH($J21,코드집!$A:$A,0)),"")
A22: 19 | B22: 2026-10-05 | C22: 북한의 눈치를 보는 게 그렇게 큰 문제일까 - 오마이뉴스 | K22: =IFERROR(INDEX(코드집!$B:$B,MATCH($J22,코드집!$A:$A,0)),"")
A23: 20 | B23: 2026-10-14 | C23: 국익·안보 중시를 事大 폄훼하고 北엔 굴종하는 李정부[사설] | 문화일보 | D23: 이재명 대통령이 13일 국무회의에서 “대한민국의 국익이 지켜지는 외교”를 강조하며 “국가 관계에 있어 굴종적 태도나 사대적 태도를 지양해야 한다”고 했다. 누가 어떤 굴종적·사대적 태도를 취하고 있다고 생각하는지 구체적으로 지칭하진 않았지만, 가깝게는 최근 한미동맹 불안 문제와 관련해 정동영·이종석 퇴진을 포함해 미국 측과 갈등 요인을 없애라는 요구 등을 겨냥한 것으로 해석된다. 더 멀리는, 진보 진영에서 거론해온 이승만 대통령이 전시 작전통제권을 미국에 넘긴 것, 박정희 대통령이 한일 수교를 결단한 것 등을 의식했을 수도 있을 것이다. | E23: 그러나 이 대통령의 굴종·사대는 궤변에 가깝다. 오히려 미국의 대북 정보 제한 조치 해소를 위한 인사 교체론이 제기되자 차단하려는 목적도 강해 보인다. 한미 연합 기밀 누출이 한미 갈등을 불렀다면 조사를 통해 정보 관리 실패 원인을 규명한 뒤 해법을 찾으면 된다. 그게 73년 동맹의 기본이다. 백악관이 “동맹 기준 준수”를 언급한 것도 그런 의미다. 한미 갈등을 해소하고 협력 틀을 만드는 것을 사대로 폄훼하면 안 된다. 그런 게 국익 외교다. | K23: =IFERROR(INDEX(코드집!$B:$B,MATCH($J23,코드집!$A:$A,0)),"")
A24: 21 | B24: 2026-10-14 | C24: [Deep dive] Lee’s core supporters can only take him so far | D24: The decline in President Lee Jae Myung’s approval rating appears to have stopped, at least for now. | E24: In a regular survey released on Sept. 30 by the Korea Society Opinion Institute, 38.5% of respondents gave Lee a positive job approval rating, while 57.8% gave him a negative rating. Two weeks earlier, the figures were 35.9% positive and 59.4% negative. | K24: =IFERROR(INDEX(코드집!$B:$B,MATCH($J24,코드집!$A:$A,0)),"")
A25: 22 | B25: 2026-09-21 | C25: Северна Корея изстреля две ракети, Южна Корея свика Съвета за нац... | D25: Редактор: Ивайло Александров | E25: Северна Корея е изстреляла балистична ракета с малък обсег, а по-късно и неидентифициран снаряд край източния си бряг в района на Вонсан, съобщава Reuters. Според японското министерство на отбраната, снарядът е паднал извън изключителната икономическа зона на Япония. | K25: =IFERROR(INDEX(코드집!$B:$B,MATCH($J25,코드집!$A:$A,0)),"")
A26: 23 | B26: 2026-09-26 | C26: SF 한인회, 비슬 무용단 초청 문화 행사 - 미주 한국일보 | D26: 판매세, 계속 올리는 것 능사 아니다 | E26: 또 다시 맞이한 ‘기나 긴 황혼녘의 투쟁’ | K26: =IFERROR(INDEX(코드집!$B:$B,MATCH($J26,코드집!$A:$A,0)),"")
A27: 24 | B27: 2026-10-06 | C27: North Korea warns of 'powerful counteraction' if South intrudes 'even a millimetre' into its territory | D27: Seoul, Oct 6 : North Korea on Tuesday warned of an "immediate and powerful counteraction" if South Korea intrudes even "a millimetre" into its territory, after Seoul signalled corresponding measures over a recent land mine blast at the inter-Korean border that it has blamed on Pyongyang. | E27: The North's foreign ministry issued the statement a day after the South's military concluded the mines planted by North Korea caused the September 21 blast on the southern side of the Demilitarised Zone (DMZ) that left two South Korean soldiers critically injured, Yonhap News Agency reported. | K27: =IFERROR(INDEX(코드집!$B:$B,MATCH($J27,코드집!$A:$A,0)),"")
A28: 25 | B28: 2026-09-25 | C28: 3 Na Hong-Jin Movies You Must See As Hope Hits Cinemas | D28: While the much-anticipated release of Avengers: Endgame Encore may be hogging the headlines this week, there is another wildly entertaining, kind of unwieldy, ridiculously ambitious near-three-hour-long sci-fi blockbuster that's got us really excited right now: Na Hong-jin's gonzo creature feature Hope . | E28: Heavily reported on as the most expensive South Korean movie ever made, Director Na's latest — which sees two police officers in a small town near the demilitarised zone between North and South Korea find themselves under attack from a mysterious creature — hits UK cinemas this week amid major hype and the promise of an experience that demands to be seen on the biggest screen possible. | K28: =IFERROR(INDEX(코드집!$B:$B,MATCH($J28,코드집!$A:$A,0)),"")
A29: 26 | B29: 2026-09-29 | C29: Zelenskiy'den çarpıcı iddia: Rusya’ya 10 bin Kuzey Kore askeri daha geliyor | Türkiye Gazetesi | D29: Ukrayna Devlet Başkanı Zelenskiy sosyal medya hesabından paylaştığı videolu mesajda, Rusya saflarında savaşan Kuzey Kore askerlerine ilişkin açıklamalarda bulundu. | E29: Zelenskiy, "Bugün Ukrayna Savunma İstihbaratından Rusya'nın bundan sonra planladığı önlemlerle ilgili bir rapor aldım. Aslında Ruslar ek seferberliğe çoktan başladı, çeşitli yollarla askere aldıkları insan sayısını artırıyorlar. Ayrıca yabancıların işe alımını artırmayı planlıyorlar. Bu ülkelerin hükümetlerinin buna karşı önlem alması önemlidir. İlgili tüm hükümetleri bilgilendireceğiz" ifadelerini kullandı. Zelenskiy, "Kuzey Kore birliklerinin Rusya'ya konuşlandırılmasıyla ilgili yeni verilere sahibiz. Şu anda Rus topraklarında 8 binden fazla Kuzey Kore askeri bulunuyor. Ayrıca 10 bin askerin daha konuşlandırılması için hazırlıklar sürüyor, bu askerler eğitimden geçirilmek ve daha sonra Rusya'ya gönderilmek üzere seçiliyor" dedi. | K29: =IFERROR(INDEX(코드집!$B:$B,MATCH($J29,코드집!$A:$A,0)),"")
A30: 27 | B30: 2026-09-28 | C30: 靑, 이례적 강경대응…“北 포로 韓행, 우크라가 먼저 비공개 요구” - 전자신문 | D30: 청와대가 북한군 포로 2명의 한국 송환 사실을 공개한 뒤 비공개 합의 자체를 부인한 우크라이나 정부에 공식 해명과 사과를 요구했다. 비공개는 당초 우크라이나 측의 요청이었다며 협상 경위를 공개하고 합의 부인이 양국 간 신뢰를 심각하게 훼손했다며 추가 조치 검토까지 예고했다. 국내에서 이재명 대통령의 거짓말 논란으로 번진 사안에 대해 우크라이나 측의 책임을 강조하며 강경 대응에 나선 셈이다. 성기홍 청와대 홍보소통수석은 27일(한국시간) 입장문을 통해 “ 우크라이나 정부 측의 합의에 위반한 일방적 공개와 이에 이은 비공개합의 사실이 없다는 허위 공보에 대해 강력한 유감을 표하며, 공식적인 해명과 사과를 요구한다”고 말했다. 앞서 볼로디미르 젤렌스키 우크라이나 대통령은 23일(현지시간) 미국 뉴욕에서 열린 유엔총회에서 북한군 포로 2명의 한국 송환 사실을 공개했다. 이후 논란이 일자 이 대통령은 X(구 트위터)를 통해 “(우크라이나가) 비공개 합의를 어겼다”고 반박했다. 하지만 우크라이나 대통령실의 한 소식통은 언론에 “비밀 유지를 약속하지 않았다”고 흘리는 등 진실 공방 양상이 빚어졌다. 동시에 국내에서도 북한군 포로 한국 송환의 비공개 여부를 두고 정치적 공방이 일었다. 이 대통령의 미국 뉴욕·멕시코 순방에 동행했던 성 수석은 입장문을 통해 그동안의 협상 과정을 대거 공개했다. 순방에 함께했던 청와대 핵심급 참모가 한국 도착 직후 입장문을 낸 것도 모자라 협상 과정을 상세하게 설명하는 것은 다소 이례적이라는 평가가 나온다. 청와대의 기조가 강경대응으로 해석되는 이유다. 청와대는 북한군 포로의 한국행 비공개는 우크라이나 정부의 요청에 따른 것이라고 강조했다. 러시아와의 협상 과정에서 북한군 포로를 거래 대상으로 활용할 기회를 포기했다는 자국 내 비판을 우려했다는 취지다. 성 수석은 “북한군 포로의 한국 송환 문제는 국제적으로나 국내적으로 안보, 외교, 국방 및 인권에 관한 매우 민감한 문제로 오랫동안 치밀하게 논의되어온 사안”이라며 “ 우크라이나 정부는 그동안 우리측과 수차례 다양한 경로를 통해 포로송환 문제를 협의하며 협의 과정에서 '한국송환 시 다수의 자국 포로들과 교환할 기회를 포기했다는 국내 비난여론이 있을 수 있는 등 매우 민감한 사안이니 한국 송환사실을 비공개하자'며 보안을 요구했다”고 설명했다. 또 “ 우리측 역시 포로 당사자와 가족들의 안전문제와 외교 안보 등 여러 측면을 고려해 비공개에 합의하고 송환 절차를 진행했다. 그런데 우크라이나 정부가 북한군 포로송환 문제에 있어 충분한 사전설명이나 구체협의 없이 일방적으로 금번 유엔총회에서 대통령 연설을 통해 북한군 포로의 한국행을 전격공개했다”고 부연했다. 특히 “ 이에 따라 국내에서 불필요한 논란이 발생하므로 이재명 대통령이 비공개 합의에 반한 공개에 대해 아쉬움을 표현하자, 이번에는 우크라이나 대통령실이 협의나 양해는 물론 사전통보조차 없이 사실과 다르게 '비공개를 합의한 적이 없다'고 발표했다. 이에 따라 국내에서는 대통령의 거짓말 논란까지 발생하고 있다”고 비판했다. 청와대는 이번 논란의 책임이 우크라이나에 있다는 입장을 다시 강조했다. 또 공식적인 해명·사과와 함께 추가적인 조치를 검토하겠다고 했다. 성 수석은 “ 우크라이나 측이 양국간 비공개합의를 어기고 사전 협의는 물론 통보조차 없이 일방적으로 공개한 것도 매우 중대한 문제지만, 우리 대통령의 사실에 기반한 정당한 공개발언에 대해 우크라이나 대통령실 공보실이 비공개 합의가 없었다는 거짓사실을 발표한 것은 양국정부간 신뢰를 심각하게 훼손하고, 양국의 우호 관계에 심대한 지장을 초래하는 행위”라고 강조했다. 또 “이 문제에 대해 추가적으로 필요한 조치를 검토 중”이라고 언급했다. 아울러 사실을 왜곡해 정쟁으로 삼는 일부 정치인들에 대해서도 경고의 메시지를 냈다. 성 수석은 “ 국내 일부 인사들이 우크라이나 정부측의 잘못을 지적하기보다 국익에 관계된 민감한 외교 안보 사안을 정쟁화하며 부당한 우크라이나측 행위를 두둔하며 국익을 훼손하는 것에 대해 깊은 유감을 표시한다. 확인되지 않은 허위주장이나 사실과 다른 주장을 삼가 주시도록 요청드린다”고 밝혔다. 최기창 기자 mobydic@etnews.com | K30: =IFERROR(INDEX(코드집!$B:$B,MATCH($J30,코드집!$A:$A,0)),"")
A31: 28 | B31: 2026-10-06 | C31: South Korean fuel shipments help Russia ease fuel crisis during Ukraine strikes | The Jerusalem Post | K31: =IFERROR(INDEX(코드집!$B:$B,MATCH($J31,코드집!$A:$A,0)),"")
A32: 29 | B32: 2026-09-25 | C32: "С большой помпой, но без прорывных результатов": В Восточной и Юго-Восточной Азии оценили итоги американо-китайского саммита - Российская газета | D32: Корейская пресса прежде всего обращает внимание на разрыв между масштабом приема Си и довольно скромными практическими результатами. "Ёнхап" сформулировал это практически предельно жестко: "Упаковка - пышный церемониал, но содержание встречи осталось скрытым"; кроме двухмесячного продления торгового перемирия заметного прогресса по Тайваню, ИИ и другим спорным вопросам агентство пока не видит. | E32: Более содержательную оценку сегодня дал сеульский East Asia Institute. Профессор Сеульского национального университета Чон Чжэ Сон считает важным само сохранение дипломатического канала и торгового перемирия, однако предупреждает: фундаментальное американо-китайское противостояние никуда не исчезло. Поэтому для Южной Кореи практический вывод - не воспринимать заявления Белого дома как окончательную стабилизацию и продолжать диверсифицировать цепочки поставок, особенно в технологическом секторе и критических материалах. | K32: =IFERROR(INDEX(코드집!$B:$B,MATCH($J32,코드집!$A:$A,0)),"")
A33: 30 | B33: 2026-09-16 | C33: KHSC gets $100,000 from car company's campaign - Kingston Whig | The Napanee Guide | D33: Kingston Health Sciences Centre is getting a $100,000 boost for pediatric cancer care from an automotive company’s national campaign, it was announced Tuesday at Kingston General Hospital. | E33: It’s the second year KHSC has received a grant through the Hyundai Hope on Wheels charitable foundation, which is distributing $4.1 million to 16 pediatric hosptials this year, up $100,000 from its inaugural year in 2025. | K33: =IFERROR(INDEX(코드집!$B:$B,MATCH($J33,코드집!$A:$A,0)),"")
A34: 31 | B34: 2026-10-19 | C34: 박완수 지사 “고용률 하락, 경남 경제 전반 진단 해야” :: 경남신문 | D34: 속보= 경남의 고용률과 취업자 수가 지난해 같은 달보다 감소한 가운데 박완수 경남도지사가 고용을 비롯한 지역경제 지표 전반에 대한 종합적인 진단을 지시했다.(19일 1면) | E34: 박 지사는 19일 오전 도청에서 열린 실국본부장회의에서 최근 발표된 경남 9월 고용동향과 관련해 “전년도 9월 고용률이 워낙 높았기 때문에 전년 동기 대비 기저효과도 있다”면서도 “현재 시점에서 경남의 고용률과 취업자 수를 비롯한 경제지표 전반에 대해 한국은행이나 유관기관과 함께 흐름과 추세를 진단하고 분석해 볼 필요가 있다”고 강조했다. 이어“취업률뿐만 아니라 다른 부분도 전반적으로 점검해 어떤 문제가 있는지 살펴봐 달라”고 주문했다. 국가데이터처 동남지방데이터청이 발표한 ‘2026년 9월 경상남도 고용동향‘에 따르면 경남의 고용률은 63.5%로 지난해 같은 달보다 0.6%p 하락했다. 취업자 수는 181만5000명으로 8000명 감소했다. 반면 실업률은 1.9%로 0.5%p 상승했고, 실업자는 3만6000명으로 1만명 증가했다. | K34: =IFERROR(INDEX(코드집!$B:$B,MATCH($J34,코드집!$A:$A,0)),"")
A35: 32 | B35: 2026-09-21 | C35: CJ제일제당, AI 시대 맞춤형 채용 컨퍼런스 ‘CJ 언바운드’ 개최... 1000명 몰렸다 | D35: CJ제일제당이 AI 시대에 맞춘 대규모 통합 채용 컨퍼런스를 개최하며 인재 확보 방식을 전면 개편했다. 기존의 일방향 설명회에서 벗어나 지원자가 직접 직무를 체험하고 현직자와 소통하는 '쌍방향 채용'으로 전환한 것이다. | E35: 21일 CJ제일제당은 지난 18일 서울 중구 CJ인재원에서 신입사원 채용 컨퍼런스 'CJ 언바운드(UNBOUND)'를 개최했다고 밝혔다. 사전 신청 첫날에만 1,000여 명이 몰릴 정도로 취업준비생들의 뜨거운 반응을 얻은 이번 행사에는 최종 추첨을 통해 선정된 300명이 참가했다. | K35: =IFERROR(INDEX(코드집!$B:$B,MATCH($J35,코드집!$A:$A,0)),"")
A36: 33 | B36: 2026-10-12 | C36: North Korea fires missiles days after South Koreaâs hypersonic test | D36: SEOUL, Oct 12 (Reuters) - North Korea fired multiple ballistic missiles toward the sea off its east coast on Monday, South Koreaâs military said, marking Pyongyangâs fourth launch in a month and following Seoulâs recent test of a hypersonic missile. | E36: By Heejin Kim and Joyce Lee The ballistic missiles, whichappeared to be of different types, were fired at around 9:20 a.m. local time (0020 GMT) from near Pyongyang, and one type flew more than 900 km (559 miles), South Korea's Joint Chiefs of Staff said. Earlier, Japan's coast guard said North Korea had fired two unidentified projectiles, believed to be ballistic missiles, adding that both appeared to have already fallen. South Korea's National Security Office convened an emergency meeting, where it condemned the missile launches as violations of United Nations Security Council resolutions and urged an immediate stop. North Korea has been under UN sanctions since 2006, aimed at halting Pyongyang's development of nuclear weapons and ballistic missiles. The latest launches come at a time when tensions have been rising between the two Koreas in recent weeks amid weapons tests by both countries. Last week, South Korean President Lee Jae Myung oversaw the country's first test-firing of a hypersonic missile , a rare public showcasing of a missile test by a South Korean president. Monday's missile launches by North Korea appeared to be "a show of force in response to the successful test launch of our hypersonic missile, as well as an intentional demonstration of missile capabilities," a spokesperson for South Korea's Joint Chiefs of Staff said. North Korea last fired a ballistic missile on October 3 , with state media KCNA saying it was a hypersonic missile tested under the supervision of leader Kim Jong Un . The tests followed a border mine blast last month that wounded three South Korean soldiers. Seoul said the landmines had been planted by North Korea and demanded an apology, but Pyongyang has dismissed this and accused South Korea of provocation. Pyongyang has conducted missile tests on more than 10 occasions this year, including four in the last month. The unusually frequent tests indicate Pyongyang wanted to increase its leverage ahead of a potential summit between leader Kim and US President Donald Trump, said Song Seong-jong, a professor at Daejeon University in Seoul and a former South Korean Defence Ministry official. "They definitely need to raise the value of their status before meeting Trump," Song said. (Reporting by Heejin Kim and Joyce Lee in Seoul, Anton Bridge in TokyoEditing by Ed Davies) | K36: =IFERROR(INDEX(코드집!$B:$B,MATCH($J36,코드집!$A:$A,0)),"")
A37: 34 | B37: 2026-10-16 | C37: Cât de departe poate merge Rusia: Volodimir Zelenski dezvălui planul lui Vladimir Putin | K37: =IFERROR(INDEX(코드집!$B:$B,MATCH($J37,코드집!$A:$A,0)),"")
A38: 35 | B38: 2026-10-08 | C38: Why U.S. And European Companies Are Investing In Asia | D38: Forbes Councils Member. | E38: Anoma Baste I MCR I Director Global Studio I Space Matrix. | K38: =IFERROR(INDEX(코드집!$B:$B,MATCH($J38,코드집!$A:$A,0)),"")
A39: 36 | B39: 2026-10-10 | C39: These 4 Android phone brands you forgot about are still making phones | D39: In the early days of Android, it seemed like every other week we'd see a completely brand-new phone from an established tech giant. Everyone was taking a stab at it. | E39: But as Android matured, a select handful of brands became the go-to choices for most buyers, namely Samsung, Google Pixel, and Motorola, while almost every other brand disappeared from the discourse. Well, as it turns out, many of those brands you think disappeared over the years are actually still making phones today, and some of them are surprisingly good. | K39: =IFERROR(INDEX(코드집!$B:$B,MATCH($J39,코드집!$A:$A,0)),"")
A40: 37 | B40: 2026-10-02 | C40: Сеул предложи на Пхенян преговори за границата | D40: 2 Октомври, 2026 06:55 1 808 2 | E40: Република Корея предложи на Северна Корея да започнат преговори за уточняване и повторно измерване на Военната демаркационна линия, разделяща двете държави. Инициативата беше отправена от министъра на обединението Чун Дон-йон на фона на напрежението след взрива на мина в Демилитаризираната зона. | K40: =IFERROR(INDEX(코드집!$B:$B,MATCH($J40,코드집!$A:$A,0)),"")
A41: 38 | B41: 2026-10-08 | C41: Who Is Going to Pay for Alaska LNG? | OilPrice.com | D41: Click Here for 150+ Global Oil Prices | E41: Click Here for 150+ Global Oil Prices | K41: =IFERROR(INDEX(코드집!$B:$B,MATCH($J41,코드집!$A:$A,0)),"")
A42: 39 | B42: 2026-09-28 | C42: 美 OCTG 반덤핑 9.8% 확정⋯세아제강, 현지 생산으로 대응 | D42: [아이뉴스24 홍성효 기자] 미국이 한국산 유정용 강관(OCTG)에 대한 반덤핑 관세를 다시 산정하면서 세아제강의 미국 수출 부담이 커졌다. 상계관세는 사실상 0% 수준을 유지하고 미국의 철강 232 관세가 높은 수준에서 적용되고 있는 만큼 세아제강지주는 미국 현지 생산과 중동 등 수출시장 다변화를 통해 통상 환경 변화에 대응한다는 전략이다. | E42: 28일 철강업계와 미국 상무부에 따르면 미국 상무부는 지난 24일 한국산 OCTG에 대한 2023~2024년 반덤핑 행정재심 최종판정에서 세아제강의 덤핑마진을 9.80%로 확정했다. 넥스틸은 29.94%, 개별 심사를 받지 않은 16개 업체에는 19.87%의 재심 특정률이 적용된다. 이번 재심 대상 기간은 2023년 9월 1일부터 2024년 8월 31일까지다. | K42: =IFERROR(INDEX(코드집!$B:$B,MATCH($J42,코드집!$A:$A,0)),"")
A43: 40 | B43: 2026-09-22 | C43: “대미투자 1호 텍사스가스발전…2호 원전·3호 알래스카”-국민일보 | K43: =IFERROR(INDEX(코드집!$B:$B,MATCH($J43,코드집!$A:$A,0)),"")
A44: 41 | B44: 2026-10-02 | C44: Trump Unveils South Korean Investment in US Energy Projects - ASEAN & Beyond En.tempo.co | D44: October 2, 2026 | 06:45 am | E44: TEMPO.CO, Jakarta - U.S. President Donald Trump has announced that South Korea will invest $200 billion in energy projects in the United States, DW reported. | K44: =IFERROR(INDEX(코드집!$B:$B,MATCH($J44,코드집!$A:$A,0)),"")
A45: 42 | B45: 2026-10-15 | C45: 삼성, 3년 연속 '亞 왕좌'… 애플·나이키 제친 브랜드 가치 - 파이낸셜뉴스 | D45: 【파이낸셜뉴스 도쿄=서혜진 특파원】 삼성전자가 아시아 브랜드 가치 조사에서 3년 연속 1위를 차지했다. 애플과 나이키를 제치고 종합 선두를 지켰지만 국가별로는 인도·베트남·인도네시아에서 2위로 내려갔다. 중국 브랜드는 품질과 디자인에 대한 평가가 높아지면서 대부분 순위가 상승했다. | E45: 아시아 8國 브랜드 가치 조사 3년째 1위 | K45: =IFERROR(INDEX(코드집!$B:$B,MATCH($J45,코드집!$A:$A,0)),"")
A46: 43 | B46: 2026-10-07 | C46: Ledakan DMZ dorong Korsel nyatakan Korut langgar gencatan senjata - ANTARA News | D46: Seoul (ANTARA) - Korea Selatan menjelaskan pihaknya berupaya menyatakan secara resmi bahwa aktivitas Korea Utara di perbatasan baru-baru ini sebagai pelanggaran Perjanjian Gencatan Senjata, menyusul penyelidikan bersama dengan Komando PBB (UNC). | E46: Kementerian Pertahanan Korea Selatan pada Rabu mengatakan langkah tersebut dilakukan setelah penyelidikan menyimpulkan bahwa ranjau yang diduga sengaja dipasang Korea Utara di sisi selatan Garis Demarkasi Militer (MDL) menyebabkan ledakan pada 21 September 2026. | K46: =IFERROR(INDEX(코드집!$B:$B,MATCH($J46,코드집!$A:$A,0)),"")
A47: 44 | B47: 2026-09-23 | C47: Ascension Parish releases a dozen NDAs involving Hyundai Steel mill | D47: DONALDSONVILLE - The Ascension Parish Government released documents on Tuesday, including a dozen NDAs involving the Hyundai Steel mill, which broke ground earlier this month. | E47: Two different types of NDAs were shared with the public, one involving Ascension Parish officials or employees and Hyundai Steel, the other involving elected officials and Louisiana Economic Development. | K47: =IFERROR(INDEX(코드집!$B:$B,MATCH($J47,코드집!$A:$A,0)),"")
A48: 45 | B48: 2026-09-18 | C48: Kuruc.info - A dél-koreai elnök szerint Trump szeretné újraindítani a párbeszédet Észak-Koreával | D48: Külföld :: 2026. szeptember 18. 06:44 :: Hozzászólások | K48: =IFERROR(INDEX(코드집!$B:$B,MATCH($J48,코드집!$A:$A,0)),"")
A49: 46 | B49: 2026-10-15 | C49: S. Korea reaffirms agreed conditions for OPCON transfer, USFK chief suggests otherwise - The Korea Herald | D49: Staff reporter at The Korea Herald’s National Desk, based in Seoul. Covers South Korea’s national security and foreign policy, with a focus on the Defense, Foreign and Unification Ministries, as well as the National Assembly. Before entering journalism, served as an Air Force officer. Experience includes providing translation and interpretation, as well as strategic input for planning efforts, at the ROK-US Combined Forces Command. During three years of military service, took part in six major South Korea-US combined exercises. | K49: =IFERROR(INDEX(코드집!$B:$B,MATCH($J49,코드집!$A:$A,0)),"")
A50: 47 | B50: 2026-09-21 | C50: Japanisches Meer - Nordkorea feuert zwei Kurzstreckenraketen ab - Südkorea beruft Sicherheitsrat ein | K50: =IFERROR(INDEX(코드집!$B:$B,MATCH($J50,코드집!$A:$A,0)),"")
A51: 48 | B51: 2026-10-11 | C51: South Korea completes first Arctic commercial voyage, targets regular route by 2030 despite risks | D51: Cutting Asia-Europe shipping times by a third, South Korea’s landmark voyage through Russian Arctic waters opens a new chapter for ports in Britain, the Netherlands, and Poland | E51: South Korea has successfully completed its first commercial round-trip voyage to Europe via the Arctic on October 11, marking a major milestone in the country's maritime ambitions. | K51: =IFERROR(INDEX(코드집!$B:$B,MATCH($J51,코드집!$A:$A,0)),"")
A52: 49 | B52: 2026-09-22 | C52: Former Twins pitcher has found new life in KBO after brutal MLB season | D52: Former Minnesota Twins pitcher Chris Paddack signed a contract with the Samsung Lions of the KBO in July after pitching for three MLB teams this year. Paddack, whom the Detroit Tigers acquired from the Twins ahead of the 2025 trade deadline, signed a one-year, $4 million deal with the Miami Marlins over the offseason. He didn't even make it to summer with the Marlins, as Miami designated the right-hander for assignment in early May . | E52: The Marlins released Paddack, 30, after he cleared waivers, allowing him to sign a deal with the Cincinnati Reds. A little over a month later, the Reds designated Paddack for assignment and released him after he cleared waivers. He then signed a contract with the Texas Rangers and appeared in just one game with the club before being DFA'd and electing free agency to sign with the KBO's Lions. Between the three MLB teams this year, Paddack posted a 6.79 ERA with a 1.67 WHIP over 57 innings. | K52: =IFERROR(INDEX(코드집!$B:$B,MATCH($J52,코드집!$A:$A,0)),"")
A53: 50 | B53: 2026-09-18 | C53: Sydkorea: Vi går inte in i Irankriget | D53: – Trump vill ha dialog och jag uppmanar också president Trump att ingå dialog, säger Lee. | E53: USA:s president har uttryckt förhoppningar om ett nytt möte med Nordkoreas diktator Kim Jong-Un. | K53: =IFERROR(INDEX(코드집!$B:$B,MATCH($J53,코드집!$A:$A,0)),"")
A54: 51 | B54: 2026-10-19 | C54: Samsung Outsources Nvidia AI Memory Base Dies to TSMC as Foundry Yields Fall Short | D54: Samsung's chief foundry rival now manufactures the most sophisticated component inside Samsung's own flagship AI memory product — a striking collapse of the vertical integration model that Samsung's memory division has relied on for decades. Seoul Economic Daily reported Sunday that Samsung Electronics agreed to source base dies for Nvidia's proprietary NVHBM memory architecture from TSMC's 3nm process, handing the contract to the Taiwanese foundry after an internal review concluded that Samsung's SF2 process cannot match TSMC's yield rates at the scale and reliability Nvidia demands. | E54: The decision confirms what semiconductor researchers have tracked for months: a roughly 40-percentage-point yield gap between Samsung's SF2 gate-all-around process (estimated at 50 to 60 percent) and TSMC's N3 FinFET node (above 90 percent, per Nvidia's brief to suppliers) has become disqualifying for Samsung Foundry at the top of the AI memory market. | K54: =IFERROR(INDEX(코드집!$B:$B,MATCH($J54,코드집!$A:$A,0)),"")
A55: 52 | B55: 2026-10-08 | C55: “맛깔리아·에이비씨”…식품업계 ‘한글’ 입고 'K푸드' 알린다 | D55: 등록 2026-10-08 오후 6:14:30 | E55: 수정 2026-10-08 오후 6:17:12 | K55: =IFERROR(INDEX(코드집!$B:$B,MATCH($J55,코드집!$A:$A,0)),"")
A56: 53 | B56: 2026-10-14 | C56: 뷰익 들어오자 달라진 쉐보레 전시장... GM의 한국 시장 ‘반격 카드’ 될까 | D56: 제너럴모터스(GM)가 뷰익의 한국 시장 진출을 계기로 기존 쉐보레 전시장을 재편하고 있다. 기존 쉐보레 전시장에 뷰익 전용 공간을 도입하고, 두 브랜드가 판매·서비스 인프라를 공유하는 방식이다. | E56: 지난 9월 국내 판매량이 727대까지 떨어진 GM 한국사업장이 새로운 브랜드와 기존 판매망을 결합해 내수시장 반등을 모색하고 있다는 분석이 나온다. | K56: =IFERROR(INDEX(코드집!$B:$B,MATCH($J56,코드집!$A:$A,0)),"")
A57: 54 | B57: 2026-10-06 | C57: Trump details US$200bil in US energy investments by South Korea | FMT | D57: Besides the Alaska LNG project and pipeline, the Trump administration announced eight new nuclear plants and a large natural gas-fired plant in Texas that would be supported by the government of South Korea, Trump said. | E57: The announcement details South Korea’s previous pledges to make good on a tariff deal with Trump. | K57: =IFERROR(INDEX(코드집!$B:$B,MATCH($J57,코드집!$A:$A,0)),"")
A58: 55 | B58: 2026-10-12 | C58: Val de rachete balistice lansat de Coreea de Nord în Marea Japoniei. Ședință de urgență la Seul - News.yam.md | D58: Armata sud-coreeană analizează specificațiile tehnice ale rachetelor nord-coreene, împreună cu specialiștii din Statele Unite, scrie hotnews.ro. | E58: Citeşte toată ştirea | K58: =IFERROR(INDEX(코드집!$B:$B,MATCH($J58,코드집!$A:$A,0)),"")
A59: 56 | B59: 2026-09-30 | C59: Seul domaga się przeprosin od Kijowa. Zełenski ujawnił tajny transfer jeńców - Bankier.pl | D59: Ukraina jako pierwsza wystąpiła o utajnienie przekazania Korei Płd. dwóch jeńców wojennych z Korei Płn., choć później sama ujawniła tę informację – przekazali w środę posłowie południowokoreańskiej komisji ds. wywiadu. | E59: – Ukraina prosiła o dyskrecję ze względu na obawę przed negatywnym wpływem ujawnienia sprawy (przekazania żołnierzy) na jej własne rokowania z Rosją dotyczące wymiany jeńców – powiedział deputowany Ju Joung Ha z opozycyjnej Partii Władzy Ludowej, relacjonując informacje ujawnione przez służbę wywiadu NIS podczas zamkniętego posiedzenia komisji parlamentarnej. | K59: =IFERROR(INDEX(코드집!$B:$B,MATCH($J59,코드집!$A:$A,0)),"")
A60: 57 | B60: 2026-09-27 | C60: США и КНР снизят взаимные пошлины на $30 млрд – Reuters - Информационное агентство Деловой журнал Профиль - profile.ru | D60: Соглашение достигнуто во время государственного визита председателя КНР Си Цзиньпина в Вашингтон, сообщает Reuters. | E60: По данным агентства, меры затронут экспорт из США сельскохозяйственной продукции, древесины и косметики, а также импорт в США мелкой бытовой техники, игрушек и предметов декора. | K60: =IFERROR(INDEX(코드집!$B:$B,MATCH($J60,코드집!$A:$A,0)),"")
A61: 58 | B61: 2026-10-09 | C61: S. Korea's materials and components reliance on Japan declined across the board since 2019 trade dispute | D61: South Korea's reliance on Japan for materials and components has been declining across the board ever since Japan intensified control on exports of key materials to South Korea in July 2019. | E61: Dependence on Japan for three key materials — high-purity hydrogen fluoride, extreme ultraviolet (EUV) photoresists, and fluorinated polyimides — has gradually declined. But South Korea still remains heavily dependent on Japan for all three of them, which analysts are pointing to as an issue to be resolved going forward. | K61: =IFERROR(INDEX(코드집!$B:$B,MATCH($J61,코드집!$A:$A,0)),"")
A62: 59 | B62: 2026-09-22 | C62: Test your knowledge of recent news events - Las Vegas Sun News | D62: The U.S. Capitol and a model of President Donald Trump's proposed Triumphal Arch are seen at the Great American State Fair, Friday, July 3, 2026, on the National Mall in Washington. Photo by: Julia Demaree Nikhinson / Associated Press | E62: Tuesday, Sept. 22, 2026 | 2 a.m. | K62: =IFERROR(INDEX(코드집!$B:$B,MATCH($J62,코드집!$A:$A,0)),"")
... A70: 67 | B70: 2026-10-16 | C70: The Galaxy S27 Ultra runs into issues with the Snapdragon 8 EE Gen 6, Exynos 2700 may return - GSMArena.com news | D70: Peter 16 October 2026 | E70: Samsung Android Rumors | K70: =IFERROR(INDEX(코드집!$B:$B,MATCH($J70,코드집!$A:$A,0)),"")
A71: 68 | B71: 2026-09-17 | C71: Is sending officials to UAE a sign Seoul is leaning towards Hormuz deployment? | K71: =IFERROR(INDEX(코드집!$B:$B,MATCH($J71,코드집!$A:$A,0)),"")
A72: 69 | B72: 2026-09-23 | C72: US-China summit: Powerful Xi presents Trump with tough choices over Iran | D72: Nine years after his meeting with Donald Trump at Mar-a-Lago in Florida, China's President Xi Jinping returns today, September 23, to the US , not as the leader of a China trying to catch up with America, but as the head of a power that has spectacularly transformed its international footprint. With a stronger technological base, massive industrial power, and critical bargaining chips in hand, Xi Jinping will speak with Trump , negotiating from a much stronger position. Indeed, China has greatly reduced its reliance on the American market while simultaneously possessing significant leverage over Washington, ranging from rare earths to artificial intelligence. The meeting takes on the character of a showdown between two sides that know neither can easily dictate terms to the other anymore. | E72: When Chinese leader Xi Jinping visits Washington this week, he will sit at the same table with President Donald Trump from an entirely different position compared to the last time the two men met face-to-face in the United States , nearly a decade ago. At the 2017 summit at Trump's Mar-a-Lago resort, China lagged behind the US in many areas and was vulnerable to the technological and trade tensions that Trump would unleash against it the following year. Now, Xi arrives as the leader of a country that has been transformed, reports CNN in its analysis. | K72: =IFERROR(INDEX(코드집!$B:$B,MATCH($J72,코드집!$A:$A,0)),"")
A73: 70 | B73: 2026-10-09 | C73: World Watch | The Shillong Times | D73: India condemns attacks on Saudi Arabia airports | E73: NEW DELHI, Oct 8: India on Thursday condemned attacks on Abha and King Khalid international airports in Saudi Arabia’s Riyadh, terming the targeting of civilian infrastructure “completely unacceptable”. The MEA offered condolences to the families of those who lost their lives in the attack and wished for a speedy recovery of those injured. “India condemns the attacks over the past few days targeting Abha International Airport and King Khalid International Airport in Riyadh, which have resulted in civilian deaths and injuries. The targeting of civilian infrastructure is completely unacceptable,” the MEA said in a statement. (IANS) | K73: =IFERROR(INDEX(코드집!$B:$B,MATCH($J73,코드집!$A:$A,0)),"")
A74: 71 | B74: 2026-09-19 | C74: Trump courts North Korea’s leader, but might need China to reignite the flame - Hawaii Tribune-Herald | D74: FILE — President Donald Trump and President Xi Jinping of China review members of the Chinese military outside the Great Hall of the People in Beijing during their two-day summit, on Thursday, May 14, 2026. Xi is reluctant to have the United States and North Korea grow closer but he could see helping broker a summit as a favor to Trump and a way to gain leverage on other U.S.-China issues, a former Trump administration official said. (Kenny Holston/The New York Times) | E74: WASHINGTON — The overtures from President Donald Trump to one of his favorite dictators came hot and heavy over the summer. | K74: =IFERROR(INDEX(코드집!$B:$B,MATCH($J74,코드집!$A:$A,0)),"")
A75: 72 | B75: 2026-10-20 | C75: Lawsuit filed over proposed funding for marine terminal near Hyundai-POSCO steel plant | D75: ASCENSION PARISH - The Port of South Louisiana is a defendant in a lawsuit challenging funding for a proposed project to support the construction of the Hyundai-POSCO Louisiana Steel Plant near Modeste in Ascension Parish. | E75: The lawsuit alleges that the port violated the Louisiana Constitution in its attempt to fund the construction of a new marine terminal near the site. | K75: =IFERROR(INDEX(코드집!$B:$B,MATCH($J75,코드집!$A:$A,0)),"")
A76: 73 | B76: 2026-10-10 | C76: What counts as security? Takaichi’s foreign policy through peace-oriented and alternative media and analysis | D76: This post is also available in: Spanish , French , Italian , German | E76: The first article ended with a question: “What is missing from this map?” After looking at Takaichi’s foreign policy from six vantage points — the United States, Europe, Australia, South Korea, China and Southeast Asia — we now shift our gaze toward peace organizations, alternative media and critical analysis. IPB, Democracy Now!, Le Monde diplomatique, Asia-Pacific Journal: Japan Focus, Bulletin of the Atomic Scientists, Foreign Policy in Focus and CounterPunch do not form a single bloc. The question is simpler: from another vantage point, what becomes visible — and what may instead escape our view? | K76: =IFERROR(INDEX(코드집!$B:$B,MATCH($J76,코드집!$A:$A,0)),"")
A77: 74 | B77: 2026-10-20 | C77: Kim Jong-Un’s sister signals 'tactical strike' in chilling border warning as leader feared dead - London Business News | Londonlovesbusiness.com | D77: North Korea has threatened to deploy additional weapons along its southern border after Kim Yo Jong, the powerful sister of leader Kim Jong-un, warned of a “grave situation” and accused South Korea of escalating military tensions. | E77: Kim’s remarks signal a further deterioration in relations between the two neighbours, with Pyongyang threatening to resume psychological warfare broadcasts and strengthen its military posture along the frontier. | K77: =IFERROR(INDEX(코드집!$B:$B,MATCH($J77,코드집!$A:$A,0)),"")
A78: 75 | B78: 2026-10-16 | C78: 韓, 9월 러시아산 LNG 수입 '2021년 11월 이후 최대'…카타르 공급 차질 여파 - 파이낸셜뉴스 | D78: [파이낸셜뉴스] 한국의 지난 9월 러시아산 액화천연가스(LNG) 수입량이 2021년 11월 이후 약 4년 10개월 만에 최대치를 기록한 것으로 나타났다. 핵심 수입국이던 카타르가 중동 지역 내 전쟁 여파로 생산을 중단하자, 이를 대체하기 위해 러시아산 수입 물량을 늘린 결과로 풀이된다. | E78: ■ 카타르 '불가항력' 선언 속 러시아산 수입 껑충 16일(현지시간) 러시아 국영 타스통신이 한국 관세청 자료를 인용해 보도한 바에 따르면, 한국은 지난 9월 러시아로부터 32만6000t(톤), 금액으로는 2억5000만달러(약 3333억원) 상당의 LNG를 수입했다. 이는 월간 수입량 기준으로 2021년 11월 이후 가장 많은 규모이며, 2022년 2월 우크라이나 전쟁 발발 이후로도 최대치다. | K78: =IFERROR(INDEX(코드집!$B:$B,MATCH($J78,코드집!$A:$A,0)),"")
A79: 76 | B79: 2026-09-28 | C79: Burkina Faso-Corée du Nord : vers un renforcement des relations bilatérales | D79: En marge de la 81e Assemblée générale de l'ONU à New York, le ministre burkinabè des Affaires étrangères, Karamoko Jean Marie Traoré, s'est entretenu le 26 septembre 2026 avec le vice-ministre nord-coréen des Affaires étrangères, Kim Son Gyong. Les deux responsables ont affiché leur volonté de dynamiser la coopération bilatérale. | E79: Au cours de cette rencontre, les discussions ont porté sur le renforcement des liens d'amitié et sur l'identification de secteurs stratégiques pour une collaboration mutuellement bénéfique. Les deux parties ont convenu d'intensifier les échanges de délégations et de consolider les cadres de coopération existants. | K79: =IFERROR(INDEX(코드집!$B:$B,MATCH($J79,코드집!$A:$A,0)),"")
A80: 77 | B80: 2026-09-27 | C80: Australia's National Statement - United States, New York | D80: SpeechTranscript Friday 25 September 2026 United States, New York | E80: The Hon Anthony Albanese MP Prime Minister of Australia | K80: =IFERROR(INDEX(코드집!$B:$B,MATCH($J80,코드집!$A:$A,0)),"")
A81: 78 | B81: 2026-09-18 | C81: « Aucune implication dans la guerre » : la Corée du Sud ne déploiera pas de forces pour se battre à Ormuz | K81: =IFERROR(INDEX(코드집!$B:$B,MATCH($J81,코드집!$A:$A,0)),"")
A82: 79 | B82: 2026-10-18 | C82: 야스쿠니 안 간 다카이치 "멀리서 절했나" 묻자 침묵 - 파이낸셜뉴스 | D82: 【파이낸셜뉴스 도쿄=서혜진 특파원】 다카이치 사나에 일본 총리가 일본 추계 예대제를 맞아 야스쿠니신사 직접 참배를 자제하면서도 총리 명의의 공물 봉납은 이어갔다. 신사 밖에서 원격 참배를 했는지에 대해서는 답변을 거부했다. 다카이치 내각 각료들도 참배에 나서도 19일에는 초당파 의원들의 집단 참배가 예정돼 있어 논란이 이어질 전망이다. | E82: 18일 산케이신문과 아사히신문, 니혼게이자이신문에 따르면 기우치 미노루 경제재정담당상은 전날 추계 예대제가 시작된 도쿄 야스쿠니신사를 참배했다. 그는 참배 후 취재진에게 "조국을 위해 고귀한 생명을 희생한 영령들에게 애도와 존경의 뜻을 전했다"며 "다시는 전쟁하지 않겠다는 결의를 새롭게 했다"고 밝혔다. 아울러 제물을 대신해 내는 돈인 다마구시료는 사비로 냈다고 설명했다. | K82: =IFERROR(INDEX(코드집!$B:$B,MATCH($J82,코드집!$A:$A,0)),"")
A83: 80 | B83: 2026-10-20 | C83: Puluhan Juta Data Pelanggan Bocor di Jepang, AI Disorot | D83: Ilustrasi Artificial Intelligence - Freepik | E83: Harianjogja.com, JOGJA — Puluhan juta catatan pelanggan dilaporkan terdampak rangkaian serangan siber di Jepang, sementara sejumlah lembaga keuangan di Korea Selatan juga menghadapi insiden peretasan. Kasus-kasus ini menempatkan keamanan data pribadi sebagai perhatian utama, terutama ketika kecerdasan buatan (AI) berpotensi membantu pelaku menemukan kelemahan sistem dengan lebih cepat. | K83: =IFERROR(INDEX(코드집!$B:$B,MATCH($J83,코드집!$A:$A,0)),"")
A84: 81 | B84: 2026-09-30 | C84: Непорядочность Киева сближает Сеул с Москвой :: В мире / ВЗГЛЯД | D84: Tекст: Геворг Мирзаян | E84: Дипломатический конфликт, возникший в на минувшей неделе между Сеулом и Киевом, продолжает разгораться. Южнокорейцы отказываются спускать на тормозах ту дипломатическую подножку, которую президенту Ли Чжэ Мену устроило киевское руководство. И уже раздумывают, чем ответить. | K84: =IFERROR(INDEX(코드집!$B:$B,MATCH($J84,코드집!$A:$A,0)),"")
A85: 82 | B85: 2026-10-02 | C85: Seoul pushes back on Trump’s Alaska LNG claims, says investment must be commercially viable | D85: On Thursday, Seoul and Washington reached an agreement on the overall framework of a US$142.3 billion strategic investment plan in the US. Their agreement covers around 70% of the US$200 billion of funding that Korea pledged to invest in the US in exchange for lower tariffs in November 2025. | E85: But US President Donald Trump’s unilateral announcement that Korea has committed to invest the remaining US$50 billion in a liquefied natural gas (LNG) project in Alaska suggests that negotiators from the two sides will continue to squabble over the details of each project. | K85: =IFERROR(INDEX(코드집!$B:$B,MATCH($J85,코드집!$A:$A,0)),"")
A86: 83 | B86: 2026-09-29 | C86: Korea Płn.: MSZ: zgoda USA na okręt atomowy dla Seulu to niebezpieczny krok | K86: =IFERROR(INDEX(코드집!$B:$B,MATCH($J86,코드집!$A:$A,0)),"")
A87: 84 | B87: 2026-09-29 | C87: Mehrheit für eigene Atomwaffe: Weniger Südkoreaner sind für Vereinigung mit Nordkorea - n-tv.de | D87: Nur 39 Prozent Südkoreaner halten eine Wiedervereinigung mit dem Norden für notwendig, wie eine Umfrage zeigt - deutlich weniger als im ersten Erhebungsjahr 2007. Eine große Mehrheit hält Dialog und Kompromiss mit der nordkoreanischen Regierung für nicht möglich. | E87: Die Unterstützung für eine Wiedervereinigung mit Nordkorea nimmt in Südkorea einer Langzeitumfrage zufolge langfristig ab. Nur mehr 39 Prozent halten eine Vereinigung der beiden koreanischen Staaten für notwendig oder eher notwendig, wie aus einer neuen Umfrage des Meinungsforschungsinstituts Gallup Korea im Auftrag der renommierten Seoul National University hervorgeht. Vor fast 20 Jahren, im ersten Erhebungsjahr 2007, lag der Wert noch bei 63,8 Prozent. Bei Südkoreanern in ihren Zwanzigern ist der Wunsch nach einer Wiedervereinigung mit 25,2 Prozent am geringsten. Zugleich befürwortet eine Mehrheit der Befragten eine eigene Atombombe. | K87: =IFERROR(INDEX(코드집!$B:$B,MATCH($J87,코드집!$A:$A,0)),"")
A88: 85 | B88: 2026-09-21 | C88: North Korea fires two ballistic missiles in three hours: South Korean military - Taipei Times | D88: North Korea yesterday launched two missiles off its eastern coast, its second set of tests in about a week and days after Pyongyang accused the US of driving tensions on the Korean Peninsula through a series of military drills. | E88: Just three hours after launching a short-range ballistic missile toward the Sea of Japan (known as the “East Sea” in South Korea and the “East Sea of Korea” in North Korea) yesterday afternoon, North Korea fired another short-range ballistic missile, the South Korean Ministry of National Defense said. | K88: =IFERROR(INDEX(코드집!$B:$B,MATCH($J88,코드집!$A:$A,0)),"")
A89: 86 | B89: 2026-09-19 | C89: North Korea Says Nuclear Status 'Irreversible' After UN Atomic Agency Rebuke | D89: Published on Saturday, 19 Sep 2026 09:46 by EO | E89: SEOUL (Reuters) - North Korean leader Kim Jong Un's powerful sister, Kim Yo Jong, accused the International Atomic Energy Agency on Saturday 19 September 2026 of double standards after it adopted a resolution criticising Pyongyang's nuclear weapons programme. The IAEA's " biased viewpoint and double standards " are " the fundamental factor causing the collapse of the international nuclear non-proliferation system ", Kim Yo Jong said in a statement in state media KCNA. She said the agency had turned a blind eye to the " blatant nuclear proliferation activities " of the United States and South Korea's " nuclear submarine introduction plan ", while forcibly adopting a resolution against North Korea's " self-defensive and legitimate nuclear activities ". In a separate KCNA statement, North Korea's Foreign Ministry also dismissed the resolution, declaring that its status as a nuclear power is irreversible and backed by its nuclear deterrent. KCNA also said North Korean leader Kim Jong Un carried out a three-day inspection tour of major munitions factories this week. Kim said North Korea's efforts to modernise all components of its defence capability are bringing about " a significant change " in the composition and means of its armed forces, KCNA said. Analysts say North Korea has been overhauling its military with Russian help since the two countries signed a mutual defence treaty in 2024. They say combat experience gained by Pyongyang's troops deployed to the war in Ukraine has also aided the effort. Kim also gave a lecture to a propaganda workers' training session in Pyongyang on Friday 18 September 2026, KCNA reported, telling attendees modern " ideological warfare " needed to be innovative, creative and aggressive rather than repeating old methods. | K89: =IFERROR(INDEX(코드집!$B:$B,MATCH($J89,코드집!$A:$A,0)),"")
A90: 87 | B90: 2026-10-20 | C90: Coreia do Sul anuncia retirada de parte do pessoal da embaixada em Kiev – ECO | D90: A Coreia do Sul anunciou hoje a retirada de parte da equipa da embaixada em Kiev, face ao adensar da disputa diplomática sobre a transferência de prisioneiros de guerra norte-coreanos para Seul . | E90: “Após a ‘convocatória’ do embaixador [sul-coreano] na Ucrânia, medida que não gerou qualquer reação construtiva por parte das autoridades ucranianas, e perante a ameaça persistente de ataques aéreos em todo o território, o que torna difícil garantir a segurança da equipa, o Governo decidiu repatriar parte dos membros da sua missão diplomática”, declarou Park Doo-soon, porta-voz do Ministério dos Negócios Estrangeiros da Coreia do Sul. | K90: =IFERROR(INDEX(코드집!$B:$B,MATCH($J90,코드집!$A:$A,0)),"")
A91: 88 | B91: 2026-09-21 | C91: Machtdemonstration vor Gipfeltreffen: Nordkorea feuert ballistische Kurzstreckenraketen ab | D91: Stand: 21.09.2026, 15:26 Uhr | E91: Kommentare Drucken Teilen | K91: =IFERROR(INDEX(코드집!$B:$B,MATCH($J91,코드집!$A:$A,0)),"")
A92: 89 | B92: 2026-10-15 | C92: 부산국제영화제, 관객 20만 명 돌파…2015년 이후 최고 기록 | K92: =IFERROR(INDEX(코드집!$B:$B,MATCH($J92,코드집!$A:$A,0)),"")
A93: 90 | B93: 2026-10-13 | C93: Fruit and vegetable exports poised to hit $10 billion in 2026 | K93: =IFERROR(INDEX(코드집!$B:$B,MATCH($J93,코드집!$A:$A,0)),"")
A94: 91 | B94: 2026-09-17 | C94: La conquista del Everest revive - Diario de Yucatán | D94: TORONTO.— Apple Original Films presentó ayer en el Festival de Cine de Toronto la película “Tenzing”. | E94: Tom Hiddleston, Willem Dafoe y Genden Phuntsok protagonizan el filme, que reconstruye la expedición que consiguió alcanzar por primera vez la cima del Monte Everest en 1953. | K94: =IFERROR(INDEX(코드집!$B:$B,MATCH($J94,코드집!$A:$A,0)),"")
A95: 92 | B95: 2026-10-07 | C95: Michelle Yeoh Calls 'Blade Runner 2099' an 'Amazing Journey' at Busan | D95: By Naman Ramachandran | E95: Michelle Yeoh turned her attention to “ Blade Runner 2099 ” at a Busan International Film Festival press conference on Wednesday, before she flies to New York Comic Con to promote the Prime Video series. | K95: =IFERROR(INDEX(코드집!$B:$B,MATCH($J95,코드집!$A:$A,0)),"")
A96: 93 | B96: 2026-10-04 | C96: Rusija sa Sjevernom Korejom dijeli naprednu vojnu tehnologiju | D96: Ukrajinski predsjednik Volodimir Zelenski rekao je u nedjelju da vjeruje kako je Rusija podijelila tehnologiju mlaznih dronova sa svojim dugogodišnjim saveznikom Sjevernom Korejom . | E96: Proteklih tjedana, Rusija je naglo povećala korištenje mlaznih dronova protiv Ukrajine, koja zasad nema učinkovitih sredstava odvraćanja osim korištenja borbenih zrakoplova. | K96: =IFERROR(INDEX(코드집!$B:$B,MATCH($J96,코드집!$A:$A,0)),"")
A97: 94 | B97: 2026-10-14 | C97: 취향 가득한 시장 '29CM DDP디자인페어' 가보니 - ZDNet korea | D97: 국내 리빙 브랜드 100여 곳 참여…올해는 테이블웨어 존재감 확대 | E97: 유통/생활/문화 입력 :2026/10/14 18:01 수정: 2026/10/14 21:12 | K97: =IFERROR(INDEX(코드집!$B:$B,MATCH($J97,코드집!$A:$A,0)),"")
A98: 95 | B98: 2026-10-08 | C98: South Korea Denies Ukrainian Report That It Eased Russia's Fuel Crisis | D98: Aerial top view of oil tanker ship at sea, Crude oil tanker industrial, Oil tanker import export business logistic, Industrial crude oil and fuel tanker ship deep blue open ocean sea. | E98: SEOUL, Oct 7 (Reuters) – South Korea’s presidential office on Wednesday dismissed a Ukrainian report that Russia has imported petroleum products from South Korean ports, calling the accusation inappropriate. | K98: =IFERROR(INDEX(코드집!$B:$B,MATCH($J98,코드집!$A:$A,0)),"")
A99: 96 | B99: 2026-10-14 | C99: "한반도 중립화는 평화 지속할 제도적 기반 마련 구상" | K99: =IFERROR(INDEX(코드집!$B:$B,MATCH($J99,코드집!$A:$A,0)),"")
A100: 97 | B100: 2026-10-21 | C100: EssilorLuxottica's smart glasses boom runs into tougher regulatory scrutiny | K100: =IFERROR(INDEX(코드집!$B:$B,MATCH($J100,코드집!$A:$A,0)),"")
A101: 98 | B101: 2026-09-23 | C101: ‘한국형 원전’ 포함 원전 8기 추진 추가비용·인력확보 최대 걸림돌 [대미투자 과제] - 헤럴드경제 | K101: =IFERROR(INDEX(코드집!$B:$B,MATCH($J101,코드집!$A:$A,0)),"")
A102: 99 | B102: 2026-10-18 | C102: Pekín y Seúl protestan por la ofrenda enviada por Takaichi al polémico santuario de Yasukuni | D102: El Gobierno de Corea del Sur y China han expresado este sábado su rechazo a la ofrenda enviada por la primera ministra japonesa, Sanae Takaichi, al santuario Yasukuni, ubicado en Tokio y considerado como un símbolo polémico del pasado imperialista de Japón. | E102: Takaichi ha enviado la ofrenda en calidad de primera ministra con motivo del inicio del otoño que celebra durante tres días este santuario bélico, el cual rinde homenaje a más de dos millones de japoneses fallecidos en las guerras, entre los que se encuentran 14 criminales de guerra condenados por tribunales internacionales debido a su participación durante la Segunda Guerra Mundial. | K102: =IFERROR(INDEX(코드집!$B:$B,MATCH($J102,코드집!$A:$A,0)),"")
A103: 100 | B103: 2026-10-06 | C103: Fuel from South Korea being shipped to Russia as Ukraine war grinds on - AOL | D103: Fuel is being shipped from South Korea to Russia via sanctioned tankers as Moscow scrambles for supplies amid the war in Ukraine, a move one expert said “undermines” Seoul’s public backing for Kyiv. | E103: Guardian analysis of port records and ship-tracking data found that in July and August over 176,000 tonnes of fuel, mostly diesel, was loaded at several South Korean ports on to seven tankers that made 14 voyages to Russia’s far east. | K103: =IFERROR(INDEX(코드집!$B:$B,MATCH($J103,코드집!$A:$A,0)),"")
A104: 101 | B104: 2026-10-12 | C104: 얀 르쿤 “실세계 이해하는 AI 필요…韓 제조 경쟁력, 세계와 연결해야” - 디지털데일리 | D104: 얀 르쿤 “실세계 이해하는 AI 필요…韓 제조 경쟁력, 세계와 연결해야” | E104: 르쿤·응우옌·아눈지아타·지미 리, 서울서 산업AI 글로벌 협력 논의 | K104: =IFERROR(INDEX(코드집!$B:$B,MATCH($J104,코드집!$A:$A,0)),"")
A105: 102 | B105: 2026-09-18 | C105: Pentagon weighs pulling at least 25,000 US troops from Europe: NBC report | D105: Possible drawdown could reach 40,000 troops as Pentagon reviews US military presence on continent | E105: The Pentagon is considering withdrawing about 25,000 or more US troops from Europe, potentially reducing the American military presence on the continent by nearly one-third, NBC News reported on Thursday. | K105: =IFERROR(INDEX(코드집!$B:$B,MATCH($J105,코드집!$A:$A,0)),"")
A106: 103 | B106: 2026-10-13 | C106: S. Korea, US, Japan hold consultations over N. Korea’s latest missile launches | K106: =IFERROR(INDEX(코드집!$B:$B,MATCH($J106,코드집!$A:$A,0)),"")
A107: 104 | B107: 2026-10-02 | C107: Best K-dramas to watch in October 2026: From Kim Yoo-jung’s historical spy romance, 100 Days of Deception to Doctor X: Mafia in White - The Economic Times | D107: ​Best K-dramas to watch in October 2026: 100 days of deception (Image: What's on Netflix) | E107: (Catch all the Business News , Breaking News , and Latest News Updates on The Economic Times .) | K107: =IFERROR(INDEX(코드집!$B:$B,MATCH($J107,코드집!$A:$A,0)),"")
...

Sheet 코드집
A1: 코드 | B1: CAMEO 공식 명칭 | C1: Goldstein
A2: 010 | B2: MAKE PUBLIC STATEMENT | C2: 0
A3: 020 | B3: APPEAL | C3: 3
A4: 030 | B4: EXPRESS INTENT TO COOPERATE | C4: 4
A5: 040 | B5: CONSULT | C5: 1
A6: 050 | B6: ENGAGE IN DIPLOMATIC COOPERATION | C6: 3.5
A7: 060 | B7: ENGAGE IN MATERIAL COOPERATION | C7: 6
A8: 070 | B8: PROVIDE AID | C8: 7
A9: 080 | B9: YIELD | C9: 5
A10: 090 | B10: INVESTIGATE | C10: -2
A11: 100 | B11: DEMAND | C11: -5
A12: 110 | B12: DISAPPROVE | C12: -2
A13: 120 | B13: REJECT | C13: -4
... A17: 160 | B17: REDUCE RELATIONS | C17: -4
A18: 170 | B18: COERCE | C18: 공표표 확인 요망
A19: 180 | B19: ASSAULT | C19: -9
A20: 190 | B20: FIGHT | C20: -10
A21: 200 | B21: USE UNCONVENTIONAL MASS VIOLENCE | C21: 공표표 확인 요망
A22: 016 | B22: Reject accusation, deny responsibility | C22: -2
A23: 025 | B23: Appeal to yield | C23: -0.3
A24: 045 | B24: Engage in mediation | C24: 5
A25: 046 | B25: Engage in negotiation | C25: 7
A26: 054 | B26: Grant diplomatic recognition | C26: 6
A27: 055 | B27: Apologize | C27: 7
A28: 057 | B28: Sign formal agreement | C28: 8
A29: 084 | B29: Return, release | C29: 7
A30: 085 | B30: Ease economic sanctions, boycott, embargo | C30: 7
A31: 087 | B31: De-escalate military engagement | C31: 9
A32: 0871 | B32: Declare truce, ceasefire | C32: 9
A33: 0874 | B33: Retreat or surrender militarily | C33: 10
... A36: 164 | B36: Halt negotiations | C36: -7
A38: 루트 20개 + 세부 15개. 목록에 없는 CAMEO 코드는 루트로 접는다 (111·112·115 -> 110, 154 -> 150, 193·194 -> 190).
